gentest.py
gentest-0.2.dist-info/top_level.txt
gentest-0.2.dist-info/RECORD
gentest-0.2.dist-info/METADATA
gentest-0.2.dist-info/WHEEL
gentest-0.2.dist-info/DESCRIPTION.rst
gentest-0.2.dist-info/metadata.json
